{
  "title": "Miss Kobayashi's Dragon Maid S",
  "synopsis": "A strange turn of events leads the Dragon, Tohru, to work as Miss Kobayashi's maid. She occasionally (that's a lie, she often) causes trouble for her beloved Miss Kobayashi while blending into human society and splendidly (that's a lie, only mediocrely) carrying out her maid duties. Her fellow dragons, Kanna, Lucoa, Fafnir, and Elma all find their own places to fit in as well and enjoy interspecies interactions with the humans. Yet while they're all enjoying that laid-back and occasionally turbulent left, the threat of a new Dragon swoops down upon Miss Kobayashi.\n\n(Source: Crunchyroll)\n",
  "thumbnail": "https://s4.anilist.co/file/anilistcdn/media/anime/cover/large/bx107717-bixaW1NTGBra.jpg",
  "synonym": "Kobayashi-san Chi no Maidragon S",
  "native": "小林さんちのメイドラゴンＳ",
  "aired": "7/8/2021",
  "premiered": "SUMMER 2021",
  "duration": "24m",
  "episodesCount": "12",
  "genres": [
    "Comedy",
    "Fantasy",
    "Slice of Life"
  ],
  "rating": "8.1",
  "type": "TV",
  "status": "FINISHED",
  "country": "JP",
  "studios": "Kyoto Animation",
  "producers": [],
  "seasons": [],
  "malId": "39247",
  "streamingId": "107717",
  "hostUrl": "https://megaplay.buzz/stream/ani",
  "episodes": [
    {
      "episode": "1",
      "title": "New Dragon, Ilulu! (Please Be Nice to Her Again)",
      "files": [
        {
          "name": "HD-1",
          "url": "https://megaplay.buzz/stream/ani/107717/1/sub",
          "type": "sub"
        },
        {
          "name": "HD-1",
          "url": "https://megaplay.buzz/stream/ani/107717/1/dub",
          "type": "dub"
        },
        {
          "name": "HD-2",
          "url": "https://megaplay.buzz/stream/mal/39247/1/sub",
          "type": "sub"
        },
        {
          "name": "HD-2",
          "url": "https://megaplay.buzz/stream/mal/39247/1/dub",
          "type": "dub"
        }
      ]
    },
    {
      "episode": "2",
      "title": "Hot Guy Kobayashi! (In Many Senses)",
      "files": [
        {
          "name": "HD-1",
          "url": "https://megaplay.buzz/stream/ani/107717/2/sub",
          "type": "sub"
        },
        {
          "name": "HD-1",
          "url": "https://megaplay.buzz/stream/ani/107717/2/dub",
          "type": "dub"
        },
        {
          "name": "HD-2",
          "url": "https://megaplay.buzz/stream/mal/39247/2/sub",
          "type": "sub"
        },
        {
          "name": "HD-2",
          "url": "https://megaplay.buzz/stream/mal/39247/2/dub",
          "type": "dub"
        }
      ]
    },
    {
      "episode": "3",
      "title": "Extracurricular Activities (Of Course They're Not Normal)",
      "files": [
        {
          "name": "HD-1",
          "url": "https://megaplay.buzz/stream/ani/107717/3/sub",
          "type": "sub"
        },
        {
          "name": "HD-1",
          "url": "https://megaplay.buzz/stream/ani/107717/3/dub",
          "type": "dub"
        },
        {
          "name": "HD-2",
          "url": "https://megaplay.buzz/stream/mal/39247/3/sub",
          "type": "sub"
        },
        {
          "name": "HD-2",
          "url": "https://megaplay.buzz/stream/mal/39247/3/dub",
          "type": "dub"
        }
      ]
    },
    {
      "episode": "4",
      "title": "When in Rome, Do as the Romans Do (It's Hard to Match Others)",
      "files": [
        {
          "name": "HD-1",
          "url": "https://megaplay.buzz/stream/ani/107717/4/sub",
          "type": "sub"
        },
        {
          "name": "HD-1",
          "url": "https://megaplay.buzz/stream/ani/107717/4/dub",
          "type": "dub"
        },
        {
          "name": "HD-2",
          "url": "https://megaplay.buzz/stream/mal/39247/4/sub",
          "type": "sub"
        },
        {
          "name": "HD-2",
          "url": "https://megaplay.buzz/stream/mal/39247/4/dub",
          "type": "dub"
        }
      ]
    },
    {
      "episode": "5",
      "title": "Together With You (Well, If We Get Along)",
      "files": [
        {
          "name": "HD-1",
          "url": "https://megaplay.buzz/stream/ani/107717/5/sub",
          "type": "sub"
        },
        {
          "name": "HD-1",
          "url": "https://megaplay.buzz/stream/ani/107717/5/dub",
          "type": "dub"
        },
        {
          "name": "HD-2",
          "url": "https://megaplay.buzz/stream/mal/39247/5/sub",
          "type": "sub"
        },
        {
          "name": "HD-2",
          "url": "https://megaplay.buzz/stream/mal/39247/5/dub",
          "type": "dub"
        }
      ]
    },
    {
      "episode": "6",
      "title": "Uncanny Relationships (One Side Is a Dragon)",
      "files": [
        {
          "name": "HD-1",
          "url": "https://megaplay.buzz/stream/ani/107717/6/sub",
          "type": "sub"
        },
        {
          "name": "HD-1",
          "url": "https://megaplay.buzz/stream/ani/107717/6/dub",
          "type": "dub"
        },
        {
          "name": "HD-2",
          "url": "https://megaplay.buzz/stream/mal/39247/6/sub",
          "type": "sub"
        },
        {
          "name": "HD-2",
          "url": "https://megaplay.buzz/stream/mal/39247/6/dub",
          "type": "dub"
        }
      ]
    },
    {
      "episode": "7",
      "title": "Common Sense (It's Different For Everyone)",
      "files": [
        {
          "name": "HD-1",
          "url": "https://megaplay.buzz/stream/ani/107717/7/sub",
          "type": "sub"
        },
        {
          "name": "HD-1",
          "url": "https://megaplay.buzz/stream/ani/107717/7/dub",
          "type": "dub"
        },
        {
          "name": "HD-2",
          "url": "https://megaplay.buzz/stream/mal/39247/7/sub",
          "type": "sub"
        },
        {
          "name": "HD-2",
          "url": "https://megaplay.buzz/stream/mal/39247/7/dub",
          "type": "dub"
        }
      ]
    },
    {
      "episode": "8",
      "title": "The World's Only (Insert Phrase You Like Here)",
      "files": [
        {
          "name": "HD-1",
          "url": "https://megaplay.buzz/stream/ani/107717/8/sub",
          "type": "sub"
        },
        {
          "name": "HD-1",
          "url": "https://megaplay.buzz/stream/ani/107717/8/dub",
          "type": "dub"
        },
        {
          "name": "HD-2",
          "url": "https://megaplay.buzz/stream/mal/39247/8/sub",
          "type": "sub"
        },
        {
          "name": "HD-2",
          "url": "https://megaplay.buzz/stream/mal/39247/8/dub",
          "type": "dub"
        }
      ]
    },
    {
      "episode": "9",
      "title": "There Are Various Reasons Behind It (It's Full of Elma)",
      "files": [
        {
          "name": "HD-1",
          "url": "https://megaplay.buzz/stream/ani/107717/9/sub",
          "type": "sub"
        },
        {
          "name": "HD-1",
          "url": "https://megaplay.buzz/stream/ani/107717/9/dub",
          "type": "dub"
        },
        {
          "name": "HD-2",
          "url": "https://megaplay.buzz/stream/mal/39247/9/sub",
          "type": "sub"
        },
        {
          "name": "HD-2",
          "url": "https://megaplay.buzz/stream/mal/39247/9/dub",
          "type": "dub"
        }
      ]
    },
    {
      "episode": "10",
      "title": "Kanna's Summer Break (Broadcast In Two Languages!?)",
      "files": [
        {
          "name": "HD-1",
          "url": "https://megaplay.buzz/stream/ani/107717/10/sub",
          "type": "sub"
        },
        {
          "name": "HD-1",
          "url": "https://megaplay.buzz/stream/ani/107717/10/dub",
          "type": "dub"
        },
        {
          "name": "HD-2",
          "url": "https://megaplay.buzz/stream/mal/39247/10/sub",
          "type": "sub"
        },
        {
          "name": "HD-2",
          "url": "https://megaplay.buzz/stream/mal/39247/10/dub",
          "type": "dub"
        }
      ]
    },
    {
      "episode": "11",
      "title": "Premium Seat (No Extra Charge)",
      "files": [
        {
          "name": "HD-1",
          "url": "https://megaplay.buzz/stream/ani/107717/11/sub",
          "type": "sub"
        },
        {
          "name": "HD-1",
          "url": "https://megaplay.buzz/stream/ani/107717/11/dub",
          "type": "dub"
        },
        {
          "name": "HD-2",
          "url": "https://megaplay.buzz/stream/mal/39247/11/sub",
          "type": "sub"
        },
        {
          "name": "HD-2",
          "url": "https://megaplay.buzz/stream/mal/39247/11/dub",
          "type": "dub"
        }
      ]
    },
    {
      "episode": "12",
      "title": "Life is Constant Change (But It's Okay To Stop And Appreciate It)",
      "files": [
        {
          "name": "HD-1",
          "url": "https://megaplay.buzz/stream/ani/107717/12/sub",
          "type": "sub"
        },
        {
          "name": "HD-1",
          "url": "https://megaplay.buzz/stream/ani/107717/12/dub",
          "type": "dub"
        },
        {
          "name": "HD-2",
          "url": "https://megaplay.buzz/stream/mal/39247/12/sub",
          "type": "sub"
        },
        {
          "name": "HD-2",
          "url": "https://megaplay.buzz/stream/mal/39247/12/dub",
          "type": "dub"
        }
      ]
    }
  ]
}