{
  "title": "Ragna Crimson",
  "synopsis": "Dragons reign terror over the earth, sea and sky. If sworn dragon hunters like Ragna are to have any hope of dealing death to these seemingly invincible, fire-breathing beasts, they must find a way to level the odds. Ragna teams up with a mysterious man named Crimson who has likewise sworn to stand against the dragons menacing the world. But although Crimson’s motivations may be mysterious, his goal and Ragna’s perfectly align, and together they’ll fight to vanquish the dragons once and for all.\n\n(Source: Sentai Filmworks)\n\nNote: The first episode aired with a runtime of ~47 minutes.",
  "thumbnail": "https://s4.anilist.co/file/anilistcdn/media/anime/cover/large/bx146493-bThyDJ4ZmbfV.jpg",
  "synonym": "Ragna Crimson",
  "native": "ラグナクリムゾン",
  "aired": "10/1/2023",
  "premiered": "FALL 2023",
  "duration": "24m",
  "episodesCount": "24",
  "genres": [
    "Action",
    "Adventure",
    "Fantasy",
    "Mystery"
  ],
  "rating": "7.4",
  "type": "TV",
  "status": "FINISHED",
  "country": "JP",
  "studios": "SILVER LINK.",
  "producers": [],
  "seasons": [],
  "malId": "51297",
  "streamingId": "146493",
  "hostUrl": "https://megaplay.buzz/stream/ani",
  "episodes": [
    {
      "episode": "1",
      "title": "The Day the Reaper was Born",
      "files": [
        {
          "name": "HD-1",
          "url": "https://megaplay.buzz/stream/ani/146493/1/sub",
          "type": "sub"
        },
        {
          "name": "HD-1",
          "url": "https://megaplay.buzz/stream/ani/146493/1/dub",
          "type": "dub"
        },
        {
          "name": "HD-2",
          "url": "https://megaplay.buzz/stream/mal/51297/1/sub",
          "type": "sub"
        },
        {
          "name": "HD-2",
          "url": "https://megaplay.buzz/stream/mal/51297/1/dub",
          "type": "dub"
        }
      ]
    },
    {
      "episode": "2",
      "title": "The Beginning of the Story",
      "files": [
        {
          "name": "HD-1",
          "url": "https://megaplay.buzz/stream/ani/146493/2/sub",
          "type": "sub"
        },
        {
          "name": "HD-1",
          "url": "https://megaplay.buzz/stream/ani/146493/2/dub",
          "type": "dub"
        },
        {
          "name": "HD-2",
          "url": "https://megaplay.buzz/stream/mal/51297/2/sub",
          "type": "sub"
        },
        {
          "name": "HD-2",
          "url": "https://megaplay.buzz/stream/mal/51297/2/dub",
          "type": "dub"
        }
      ]
    },
    {
      "episode": "3",
      "title": "Agitation",
      "files": [
        {
          "name": "HD-1",
          "url": "https://megaplay.buzz/stream/ani/146493/3/sub",
          "type": "sub"
        },
        {
          "name": "HD-1",
          "url": "https://megaplay.buzz/stream/ani/146493/3/dub",
          "type": "dub"
        },
        {
          "name": "HD-2",
          "url": "https://megaplay.buzz/stream/mal/51297/3/sub",
          "type": "sub"
        },
        {
          "name": "HD-2",
          "url": "https://megaplay.buzz/stream/mal/51297/3/dub",
          "type": "dub"
        }
      ]
    },
    {
      "episode": "4",
      "title": "Action",
      "files": [
        {
          "name": "HD-1",
          "url": "https://megaplay.buzz/stream/ani/146493/4/sub",
          "type": "sub"
        },
        {
          "name": "HD-1",
          "url": "https://megaplay.buzz/stream/ani/146493/4/dub",
          "type": "dub"
        },
        {
          "name": "HD-2",
          "url": "https://megaplay.buzz/stream/mal/51297/4/sub",
          "type": "sub"
        },
        {
          "name": "HD-2",
          "url": "https://megaplay.buzz/stream/mal/51297/4/dub",
          "type": "dub"
        }
      ]
    },
    {
      "episode": "5",
      "title": "Wing",
      "files": [
        {
          "name": "HD-1",
          "url": "https://megaplay.buzz/stream/ani/146493/5/sub",
          "type": "sub"
        },
        {
          "name": "HD-1",
          "url": "https://megaplay.buzz/stream/ani/146493/5/dub",
          "type": "dub"
        },
        {
          "name": "HD-2",
          "url": "https://megaplay.buzz/stream/mal/51297/5/sub",
          "type": "sub"
        },
        {
          "name": "HD-2",
          "url": "https://megaplay.buzz/stream/mal/51297/5/dub",
          "type": "dub"
        }
      ]
    },
    {
      "episode": "6",
      "title": "Reunion",
      "files": [
        {
          "name": "HD-1",
          "url": "https://megaplay.buzz/stream/ani/146493/6/sub",
          "type": "sub"
        },
        {
          "name": "HD-1",
          "url": "https://megaplay.buzz/stream/ani/146493/6/dub",
          "type": "dub"
        },
        {
          "name": "HD-2",
          "url": "https://megaplay.buzz/stream/mal/51297/6/sub",
          "type": "sub"
        },
        {
          "name": "HD-2",
          "url": "https://megaplay.buzz/stream/mal/51297/6/dub",
          "type": "dub"
        }
      ]
    },
    {
      "episode": "7",
      "title": "Act and Guilt",
      "files": [
        {
          "name": "HD-1",
          "url": "https://megaplay.buzz/stream/ani/146493/7/sub",
          "type": "sub"
        },
        {
          "name": "HD-1",
          "url": "https://megaplay.buzz/stream/ani/146493/7/dub",
          "type": "dub"
        },
        {
          "name": "HD-2",
          "url": "https://megaplay.buzz/stream/mal/51297/7/sub",
          "type": "sub"
        },
        {
          "name": "HD-2",
          "url": "https://megaplay.buzz/stream/mal/51297/7/dub",
          "type": "dub"
        }
      ]
    },
    {
      "episode": "8",
      "title": "A Painful Blow",
      "files": [
        {
          "name": "HD-1",
          "url": "https://megaplay.buzz/stream/ani/146493/8/sub",
          "type": "sub"
        },
        {
          "name": "HD-1",
          "url": "https://megaplay.buzz/stream/ani/146493/8/dub",
          "type": "dub"
        },
        {
          "name": "HD-2",
          "url": "https://megaplay.buzz/stream/mal/51297/8/sub",
          "type": "sub"
        },
        {
          "name": "HD-2",
          "url": "https://megaplay.buzz/stream/mal/51297/8/dub",
          "type": "dub"
        }
      ]
    },
    {
      "episode": "9",
      "title": "Negotiation and True Nature",
      "files": [
        {
          "name": "HD-1",
          "url": "https://megaplay.buzz/stream/ani/146493/9/sub",
          "type": "sub"
        },
        {
          "name": "HD-1",
          "url": "https://megaplay.buzz/stream/ani/146493/9/dub",
          "type": "dub"
        },
        {
          "name": "HD-2",
          "url": "https://megaplay.buzz/stream/mal/51297/9/sub",
          "type": "sub"
        },
        {
          "name": "HD-2",
          "url": "https://megaplay.buzz/stream/mal/51297/9/dub",
          "type": "dub"
        }
      ]
    },
    {
      "episode": "10",
      "title": "Stakes and Cooperation",
      "files": [
        {
          "name": "HD-1",
          "url": "https://megaplay.buzz/stream/ani/146493/10/sub",
          "type": "sub"
        },
        {
          "name": "HD-1",
          "url": "https://megaplay.buzz/stream/ani/146493/10/dub",
          "type": "dub"
        },
        {
          "name": "HD-2",
          "url": "https://megaplay.buzz/stream/mal/51297/10/sub",
          "type": "sub"
        },
        {
          "name": "HD-2",
          "url": "https://megaplay.buzz/stream/mal/51297/10/dub",
          "type": "dub"
        }
      ]
    },
    {
      "episode": "11",
      "title": "Tactics and Knowledge",
      "files": [
        {
          "name": "HD-1",
          "url": "https://megaplay.buzz/stream/ani/146493/11/sub",
          "type": "sub"
        },
        {
          "name": "HD-1",
          "url": "https://megaplay.buzz/stream/ani/146493/11/dub",
          "type": "dub"
        },
        {
          "name": "HD-2",
          "url": "https://megaplay.buzz/stream/mal/51297/11/sub",
          "type": "sub"
        },
        {
          "name": "HD-2",
          "url": "https://megaplay.buzz/stream/mal/51297/11/dub",
          "type": "dub"
        }
      ]
    },
    {
      "episode": "12",
      "title": "Determination and Readiness",
      "files": [
        {
          "name": "HD-1",
          "url": "https://megaplay.buzz/stream/ani/146493/12/sub",
          "type": "sub"
        },
        {
          "name": "HD-1",
          "url": "https://megaplay.buzz/stream/ani/146493/12/dub",
          "type": "dub"
        },
        {
          "name": "HD-2",
          "url": "https://megaplay.buzz/stream/mal/51297/12/sub",
          "type": "sub"
        },
        {
          "name": "HD-2",
          "url": "https://megaplay.buzz/stream/mal/51297/12/dub",
          "type": "dub"
        }
      ]
    },
    {
      "episode": "13",
      "title": "Hero of the Battle",
      "files": [
        {
          "name": "HD-1",
          "url": "https://megaplay.buzz/stream/ani/146493/13/sub",
          "type": "sub"
        },
        {
          "name": "HD-1",
          "url": "https://megaplay.buzz/stream/ani/146493/13/dub",
          "type": "dub"
        },
        {
          "name": "HD-2",
          "url": "https://megaplay.buzz/stream/mal/51297/13/sub",
          "type": "sub"
        },
        {
          "name": "HD-2",
          "url": "https://megaplay.buzz/stream/mal/51297/13/dub",
          "type": "dub"
        }
      ]
    },
    {
      "episode": "14",
      "title": "Impatience and Vigilance",
      "files": [
        {
          "name": "HD-1",
          "url": "https://megaplay.buzz/stream/ani/146493/14/sub",
          "type": "sub"
        },
        {
          "name": "HD-1",
          "url": "https://megaplay.buzz/stream/ani/146493/14/dub",
          "type": "dub"
        },
        {
          "name": "HD-2",
          "url": "https://megaplay.buzz/stream/mal/51297/14/sub",
          "type": "sub"
        },
        {
          "name": "HD-2",
          "url": "https://megaplay.buzz/stream/mal/51297/14/dub",
          "type": "dub"
        }
      ]
    },
    {
      "episode": "15",
      "title": "Latent Awakening",
      "files": [
        {
          "name": "HD-1",
          "url": "https://megaplay.buzz/stream/ani/146493/15/sub",
          "type": "sub"
        },
        {
          "name": "HD-1",
          "url": "https://megaplay.buzz/stream/ani/146493/15/dub",
          "type": "dub"
        },
        {
          "name": "HD-2",
          "url": "https://megaplay.buzz/stream/mal/51297/15/sub",
          "type": "sub"
        },
        {
          "name": "HD-2",
          "url": "https://megaplay.buzz/stream/mal/51297/15/dub",
          "type": "dub"
        }
      ]
    },
    {
      "episode": "16",
      "title": "Will of Resistance",
      "files": [
        {
          "name": "HD-1",
          "url": "https://megaplay.buzz/stream/ani/146493/16/sub",
          "type": "sub"
        },
        {
          "name": "HD-1",
          "url": "https://megaplay.buzz/stream/ani/146493/16/dub",
          "type": "dub"
        },
        {
          "name": "HD-2",
          "url": "https://megaplay.buzz/stream/mal/51297/16/sub",
          "type": "sub"
        },
        {
          "name": "HD-2",
          "url": "https://megaplay.buzz/stream/mal/51297/16/dub",
          "type": "dub"
        }
      ]
    },
    {
      "episode": "17",
      "title": "My Comrade",
      "files": [
        {
          "name": "HD-1",
          "url": "https://megaplay.buzz/stream/ani/146493/17/sub",
          "type": "sub"
        },
        {
          "name": "HD-1",
          "url": "https://megaplay.buzz/stream/ani/146493/17/dub",
          "type": "dub"
        },
        {
          "name": "HD-2",
          "url": "https://megaplay.buzz/stream/mal/51297/17/sub",
          "type": "sub"
        },
        {
          "name": "HD-2",
          "url": "https://megaplay.buzz/stream/mal/51297/17/dub",
          "type": "dub"
        }
      ]
    },
    {
      "episode": "18",
      "title": "End of the Battle to the Death",
      "files": [
        {
          "name": "HD-1",
          "url": "https://megaplay.buzz/stream/ani/146493/18/sub",
          "type": "sub"
        },
        {
          "name": "HD-1",
          "url": "https://megaplay.buzz/stream/ani/146493/18/dub",
          "type": "dub"
        },
        {
          "name": "HD-2",
          "url": "https://megaplay.buzz/stream/mal/51297/18/sub",
          "type": "sub"
        },
        {
          "name": "HD-2",
          "url": "https://megaplay.buzz/stream/mal/51297/18/dub",
          "type": "dub"
        }
      ]
    },
    {
      "episode": "19",
      "title": "Reason to Fight",
      "files": [
        {
          "name": "HD-1",
          "url": "https://megaplay.buzz/stream/ani/146493/19/sub",
          "type": "sub"
        },
        {
          "name": "HD-1",
          "url": "https://megaplay.buzz/stream/ani/146493/19/dub",
          "type": "dub"
        },
        {
          "name": "HD-2",
          "url": "https://megaplay.buzz/stream/mal/51297/19/sub",
          "type": "sub"
        },
        {
          "name": "HD-2",
          "url": "https://megaplay.buzz/stream/mal/51297/19/dub",
          "type": "dub"
        }
      ]
    },
    {
      "episode": "20",
      "title": "Just Watch Me",
      "files": [
        {
          "name": "HD-1",
          "url": "https://megaplay.buzz/stream/ani/146493/20/sub",
          "type": "sub"
        },
        {
          "name": "HD-1",
          "url": "https://megaplay.buzz/stream/ani/146493/20/dub",
          "type": "dub"
        },
        {
          "name": "HD-2",
          "url": "https://megaplay.buzz/stream/mal/51297/20/sub",
          "type": "sub"
        },
        {
          "name": "HD-2",
          "url": "https://megaplay.buzz/stream/mal/51297/20/dub",
          "type": "dub"
        }
      ]
    },
    {
      "episode": "21",
      "title": "Words Aren't Needed",
      "files": [
        {
          "name": "HD-1",
          "url": "https://megaplay.buzz/stream/ani/146493/21/sub",
          "type": "sub"
        },
        {
          "name": "HD-1",
          "url": "https://megaplay.buzz/stream/ani/146493/21/dub",
          "type": "dub"
        },
        {
          "name": "HD-2",
          "url": "https://megaplay.buzz/stream/mal/51297/21/sub",
          "type": "sub"
        },
        {
          "name": "HD-2",
          "url": "https://megaplay.buzz/stream/mal/51297/21/dub",
          "type": "dub"
        }
      ]
    },
    {
      "episode": "22",
      "title": "The Winged Monarch",
      "files": [
        {
          "name": "HD-1",
          "url": "https://megaplay.buzz/stream/ani/146493/22/sub",
          "type": "sub"
        },
        {
          "name": "HD-1",
          "url": "https://megaplay.buzz/stream/ani/146493/22/dub",
          "type": "dub"
        },
        {
          "name": "HD-2",
          "url": "https://megaplay.buzz/stream/mal/51297/22/sub",
          "type": "sub"
        },
        {
          "name": "HD-2",
          "url": "https://megaplay.buzz/stream/mal/51297/22/dub",
          "type": "dub"
        }
      ]
    },
    {
      "episode": "23",
      "title": "Lightning God",
      "files": [
        {
          "name": "HD-1",
          "url": "https://megaplay.buzz/stream/ani/146493/23/sub",
          "type": "sub"
        },
        {
          "name": "HD-1",
          "url": "https://megaplay.buzz/stream/ani/146493/23/dub",
          "type": "dub"
        },
        {
          "name": "HD-2",
          "url": "https://megaplay.buzz/stream/mal/51297/23/sub",
          "type": "sub"
        },
        {
          "name": "HD-2",
          "url": "https://megaplay.buzz/stream/mal/51297/23/dub",
          "type": "dub"
        }
      ]
    },
    {
      "episode": "24",
      "title": "Light",
      "files": [
        {
          "name": "HD-1",
          "url": "https://megaplay.buzz/stream/ani/146493/24/sub",
          "type": "sub"
        },
        {
          "name": "HD-1",
          "url": "https://megaplay.buzz/stream/ani/146493/24/dub",
          "type": "dub"
        },
        {
          "name": "HD-2",
          "url": "https://megaplay.buzz/stream/mal/51297/24/sub",
          "type": "sub"
        },
        {
          "name": "HD-2",
          "url": "https://megaplay.buzz/stream/mal/51297/24/dub",
          "type": "dub"
        }
      ]
    }
  ]
}