{
  "title": "Ascendance of a Bookworm: Adopted Daughter of an Archduke",
  "synopsis": "Anime adaptation of Part 3 of Honzuki no Gekokujou.\n\\n\\n\nFollowing a disastrous encounter with a noble, Myne finally resolves to say goodbye to her family and friends in the lower city, changing her name to “Rozemyne” and beginning her new life as the adopted daughter of Ehrenfest’s archduke. However, her days as an archnoble in noble society are brutal, as she is put through rigorous etiquette and magic training on top of her duties as High Bishop and forewoman. It all proves too much for a weak little seven-year-old girl... Or it would have, had the High Priest not offered her the keys to the temple’s book room as a reward. If she could get her hands on those, she’d be able to read all sorts of precious books! Her name may have changed, but Rozemyne’s passion for books remains the same as she charges into a whole new world! The detailed setting expands as the printing industry grows in size. Here begins Part 3 of this biblio-fantasy for book lovers everywhere!\n\\n\\n\n(Source: J-Novel Club) ",
  "thumbnail": "https://s4.anilist.co/file/anilistcdn/media/anime/cover/large/bx171110-7zOdInS6DQNL.jpg",
  "synonym": "",
  "native": "",
  "aired": "",
  "premiered": "",
  "duration": "",
  "episodesCount": "0",
  "genres": [
    "Drama",
    "Fantasy",
    "Slice of Life"
  ],
  "rating": "",
  "type": "TV Series",
  "status": "Ongoing",
  "country": "JP",
  "studios": [
    "WIT STUDIO"
  ],
  "producers": [],
  "seasons": [
    {
      "title": "[TV Series] Ascendance of a Bookworm: Adopted Daughter of an Archduke",
      "link": "/2026/04/171110.html",
      "poster": "https://s4.anilist.co/file/anilistcdn/media/anime/cover/large/bx171110-7zOdInS6DQNL.jpg"
    },
    {
      "title": "[TV Series] Ascendance of a Bookworm Season 3",
      "link": "/2022/04/121176.html",
      "poster": "https://s4.anilist.co/file/anilistcdn/media/anime/cover/medium/bx121176-qWobMmSf761W.jpg"
    }
  ],
  "episodes": [],
  "streamingId": "171110",
  "releaseDate": "2026-04-04",
  "malId": "",
  "hostUrl": "https://megaplay.buzz/stream/ani"
}