{
  "title": "ONE PIECE",
  "synopsis": "Gold Roger was known as the Pirate King, the strongest and most infamous being to have sailed the Grand Line. The capture and death of Roger by the World Government brought a change throughout the world. His last words before his death revealed the location of the greatest treasure in the world, One Piece. It was this revelation that brought about the Grand Age of Pirates, men who dreamed of finding One Piece (which promises an unlimited amount of riches and fame), and quite possibly the most coveted of titles for the person who found it, the title of the Pirate King.\\n\\n\nEnter Monkey D. Luffy, a 17-year-old boy that defies your standard definition of a pirate. Rather than the popular persona of a wicked, hardened, toothless pirate who ransacks villages for fun, Luffy’s reason for being a pirate is one of pure wonder; the thought of an exciting adventure and meeting new and intriguing people, along with finding One Piece, are his reasons of becoming a pirate. Following in the footsteps of his childhood hero, Luffy and his crew travel across the Grand Line, experiencing crazy adventures, unveiling dark mysteries and battling strong enemies, all in order to reach One Piece.\\n\\n\n*This includes the following special episodes:\\n\n- Chopperman to the Rescue! Protect the TV Station by the Shore! (Episode 336)\\n\n- The Strongest Tag-Team! Luffy and Toriko's Hard Struggle! (Episode 492)\\n\n- Team Formation! Save Chopper (Episode 542)\\n\n- History's Strongest Collaboration vs. Glutton of the Sea (Episode 590)\\n\n- 20th Anniversary! Special Romance Dawn (Episode 907)",
  "thumbnail": "https://s4.anilist.co/file/anilistcdn/media/anime/cover/large/bx21-ELSYx3yMPcKM.jpg",
  "synonym": "",
  "native": "",
  "aired": "",
  "premiered": "",
  "duration": "",
  "episodesCount": "0",
  "genres": [
    "Action",
    "Adventure",
    "Comedy",
    "Drama",
    "Fantasy"
  ],
  "rating": "",
  "type": "TV Series",
  "status": "Ongoing",
  "country": "JP",
  "studios": [
    "Toei Animation"
  ],
  "producers": [],
  "seasons": [
    {
      "title": "[TV Series] ONE PIECE",
      "link": "/1999/10/21.html",
      "poster": "https://s4.anilist.co/file/anilistcdn/media/anime/cover/large/bx21-ELSYx3yMPcKM.jpg"
    },
    {
      "title": "[OVA] One Piece: Defeat the Pirate Ganzack!",
      "link": "/1998/07/466.html",
      "poster": "https://s4.anilist.co/file/anilistcdn/media/anime/cover/medium/nx466-bVP54I7dCB2F.jpg"
    },
    {
      "title": "[Special] One Piece: Umi no Heso no Daibouken-hen",
      "link": "/2000/12/1094.html",
      "poster": "https://s4.anilist.co/file/anilistcdn/media/anime/cover/medium/bx1094-H3YFJ1TR0ZZi.jpg"
    },
    {
      "title": "[Special] One Piece Special: Open Upon the Great Sea! A Father's Huge, HUGE Dream!",
      "link": "/2003/04/1237.html",
      "poster": "https://s4.anilist.co/file/anilistcdn/media/anime/cover/medium/1237.jpg"
    },
    {
      "title": "[Special] One Piece Special: Protect! The Last Great Performance",
      "link": "/2003/12/1238.html",
      "poster": "https://s4.anilist.co/file/anilistcdn/media/anime/cover/medium/bx1238-Rf2wqBrCwgvO.jpg"
    },
    {
      "title": "[Special] One Piece Special: The Detective Memoirs of Chief Straw Hat Luffy",
      "link": "/2005/12/2020.html",
      "poster": "https://s4.anilist.co/file/anilistcdn/media/anime/cover/medium/2020.jpg"
    },
    {
      "title": "[Special] ONE PIECE: Yume no Soccer Ou!",
      "link": "/2002/03/2386.html",
      "poster": "https://s4.anilist.co/file/anilistcdn/media/anime/cover/medium/2386-NQQkq1taHJ08.jpg"
    },
    {
      "title": "[Special] ONE PIECE: Mezase! Kaizoku Yakyuu Ou",
      "link": "/2004/03/2490.html",
      "poster": "https://s4.anilist.co/file/anilistcdn/media/anime/cover/medium/2490-AL4WmnCJ5zvE.jpg"
    },
    {
      "title": "[Movie] ONE PIECE 3D: Gekisou! Trap Coaster",
      "link": "/2011/12/12001.html",
      "poster": "https://s4.anilist.co/file/anilistcdn/media/anime/cover/medium/nx12001-XX0NNNfaKZ3e.jpg"
    },
    {
      "title": "[Special] One Piece: Episode of Luffy - Hand Island Adventure",
      "link": "/2012/12/16239.html",
      "poster": "https://s4.anilist.co/file/anilistcdn/media/anime/cover/medium/b16239-XzoVjd7JK8xJ.png"
    },
    {
      "title": "[Special] ONE PIECE FILM: Z - GLORIOUS ISLAND",
      "link": "/2012/12/16468.html",
      "poster": "https://s4.anilist.co/file/anilistcdn/media/anime/cover/medium/b16468-pMKFwfY8lYZX.png"
    },
    {
      "title": "[Special] ONE PIECE: Episode of Nami - Koukaishi no Namida to Nakama no Kizuna",
      "link": "/2012/08/15323.html",
      "poster": "https://s4.anilist.co/file/anilistcdn/media/anime/cover/medium/15323.jpg"
    },
    {
      "title": "[Special] One Piece: Episode of Merry - The Tale of One More Friend",
      "link": "/2013/08/19123.html",
      "poster": "https://s4.anilist.co/file/anilistcdn/media/anime/cover/medium/nx19123-leET1CrSJknT.jpg"
    },
    {
      "title": "[Special] One Piece 3D2Y: Overcome Ace’s Death! Luffy’s Vow to his Friends",
      "link": "/2014/08/20835.html",
      "poster": "https://s4.anilist.co/file/anilistcdn/media/anime/cover/medium/bx20835-QVV6LpJlqe1A.jpg"
    },
    {
      "title": "[Special] One Piece - Episode of Sabo: Bond of Three Brothers - A Miraculous Reunion and an Inherited Will",
      "link": "/2015/08/21230.html",
      "poster": "https://s4.anilist.co/file/anilistcdn/media/anime/cover/medium/bx21230-rfoUZud1Jn0L.png"
    },
    {
      "title": "[Special] One Piece: Adventure of Nebulandia",
      "link": "/2015/12/21485.html",
      "poster": "https://s4.anilist.co/file/anilistcdn/media/anime/cover/medium/21485-KR1sv4rYSe6V.jpg"
    },
    {
      "title": "[Special] One Piece: Heart of Gold",
      "link": "/2016/07/21831.html",
      "poster": "https://s4.anilist.co/file/anilistcdn/media/anime/cover/medium/bx21831-qj5IKYiPOupF.jpg"
    },
    {
      "title": "[Special] One Piece: Episode of East Blue",
      "link": "/2017/08/99302.html",
      "poster": "https://s4.anilist.co/file/anilistcdn/media/anime/cover/medium/bx99302-b40WIhc5dylo.jpg"
    },
    {
      "title": "[Movie] ONE PIECE: The Movie",
      "link": "/2000/03/459.html",
      "poster": "https://s4.anilist.co/file/anilistcdn/media/anime/cover/medium/bx459-Ivw65mUXackh.png"
    },
    {
      "title": "[Movie] One Piece: Clockwork Island Adventure",
      "link": "/2001/03/460.html",
      "poster": "https://s4.anilist.co/file/anilistcdn/media/anime/cover/medium/bx460-p9HObfGUhWn0.jpg"
    },
    {
      "title": "[Movie] One Piece: Chopper’s Kingdom on the Island of Strange Animals",
      "link": "/2002/03/461.html",
      "poster": "https://s4.anilist.co/file/anilistcdn/media/anime/cover/medium/bx461-DC9fMDl3AaK1.jpg"
    },
    {
      "title": "[Movie] One Piece The Movie: The Dead End Adventure",
      "link": "/2003/03/462.html",
      "poster": "https://s4.anilist.co/file/anilistcdn/media/anime/cover/medium/bx462-Ig8zfdsFWcql.png"
    },
    {
      "title": "[Movie] One Piece: The Curse of the Sacred Sword",
      "link": "/2004/03/463.html",
      "poster": "https://s4.anilist.co/file/anilistcdn/media/anime/cover/medium/nx463-QDnETPoHp9oD.jpg"
    },
    {
      "title": "[Movie] One Piece: Baron Omatsuri and the Secret Island",
      "link": "/2005/03/464.html",
      "poster": "https://s4.anilist.co/file/anilistcdn/media/anime/cover/medium/bx464-g4wcZPjbhY5j.png"
    },
    {
      "title": "[Movie] One Piece: Mega Mecha Soldier of Karakuri Castle",
      "link": "/2006/03/465.html",
      "poster": "https://s4.anilist.co/file/anilistcdn/media/anime/cover/medium/bx465-qSRr0MKYhS0I.jpg"
    },
    {
      "title": "[Movie] One Piece: The Desert Princess and the Pirates, Adventures in Alabasta",
      "link": "/2007/03/2107.html",
      "poster": "https://s4.anilist.co/file/anilistcdn/media/anime/cover/medium/bx2107-H8bRuRRbhCIJ.jpg"
    },
    {
      "title": "[Movie] One Piece: Episode Of Chopper +: The Miracle Winter Cherry Blossom",
      "link": "/2008/03/3848.html",
      "poster": "https://s4.anilist.co/file/anilistcdn/media/anime/cover/medium/bx3848-SCnYGTn34Llt.jpg"
    },
    {
      "title": "[Movie] One Piece Film: Strong World",
      "link": "/2009/12/4155.html",
      "poster": "https://s4.anilist.co/file/anilistcdn/media/anime/cover/medium/bx4155-P5TDf6t6qFwX.png"
    },
    {
      "title": "[Movie] One Piece 3D: Mugiwara Chase",
      "link": "/2011/03/9999.html",
      "poster": "https://s4.anilist.co/file/anilistcdn/media/anime/cover/medium/9999.jpg"
    },
    {
      "title": "[Movie] One Piece Film: Z",
      "link": "/2012/12/12859.html",
      "poster": "https://s4.anilist.co/file/anilistcdn/media/anime/cover/medium/bx12859-uQFENDPzMWz6.jpg"
    },
    {
      "title": "[Movie] One Piece Film: Gold",
      "link": "/2016/07/21335.html",
      "poster": "https://s4.anilist.co/file/anilistcdn/media/anime/cover/medium/nx21335-XsXdE0AeOkkZ.jpg"
    },
    {
      "title": "[Special] One Piece: Episode of Skypiea",
      "link": "/2018/08/101918.html",
      "poster": "https://s4.anilist.co/file/anilistcdn/media/anime/cover/medium/bx101918-3uyCYHw1syki.png"
    },
    {
      "title": "[OVA] ONE PIECE FILM: STRONG WORLD - EPISODE:0",
      "link": "/2010/04/8740.html",
      "poster": "https://s4.anilist.co/file/anilistcdn/media/anime/cover/medium/b8740-oZajT3brPn7b.jpg"
    },
    {
      "title": "[Movie] One Piece: Stampede",
      "link": "/2019/08/105143.html",
      "poster": "https://s4.anilist.co/file/anilistcdn/media/anime/cover/medium/bx105143-5uBDmhvMr6At.png"
    },
    {
      "title": "[Special] ONE PIECE: Episode of Alabasta - Sabaku no Oujo to Kaizoku-tachi",
      "link": "/2011/08/106572.html",
      "poster": "https://s4.anilist.co/file/anilistcdn/media/anime/cover/medium/n106572-k1gqIsDcqGaV.jpg"
    },
    {
      "title": "[Special] One Piece: Django's Dance Carnival",
      "link": "/2001/03/2385.html",
      "poster": "https://s4.anilist.co/file/anilistcdn/media/anime/cover/medium/bx2385-06iBj9aNIadt.jpg"
    },
    {
      "title": "[Special] ONE PIECE FILM: GOLD - episode 0 711ver.",
      "link": "/2016/07/21880.html",
      "poster": "https://s4.anilist.co/file/anilistcdn/media/anime/cover/medium/nx21880-uxsZ880LXSdY.jpg"
    },
    {
      "title": "[OVA] One Piece: Romance Dawn Story",
      "link": "/2008/11/5252.html",
      "poster": "https://s4.anilist.co/file/anilistcdn/media/anime/cover/medium/5252.jpg"
    },
    {
      "title": "[Movie] The Great Tongari Island Treasure Hunting Adventure",
      "link": "/2016/11/126649.html",
      "poster": "https://s4.anilist.co/file/anilistcdn/media/anime/cover/medium/b126649-sbuKTAghtsln.jpg"
    },
    {
      "title": "[Movie] One Piece Film: Red",
      "link": "/2022/08/141902.html",
      "poster": "https://s4.anilist.co/file/anilistcdn/media/anime/cover/medium/bx141902-fTyoTk8F8qOl.jpg"
    },
    {
      "title": "[ONA] MONSTERS: 103 Mercies Dragon Damnation",
      "link": "/2024/01/167404.html",
      "poster": "https://s4.anilist.co/file/anilistcdn/media/anime/cover/medium/bx167404-QMZJVARntkbv.jpg"
    },
    {
      "title": "[TV Series] THE ONE PIECE",
      "link": "/2027/02/171630.html",
      "poster": "https://s4.anilist.co/file/anilistcdn/media/anime/cover/medium/bx171630-CW3kbduXmmUE.jpg"
    },
    {
      "title": "[Special] ONE PIECE FAN LETTER",
      "link": "/2024/10/182469.html",
      "poster": "https://s4.anilist.co/file/anilistcdn/media/anime/cover/medium/bx182469-JQ808NBPxmgn.jpg"
    },
    {
      "title": "[TV Series] One Piece Log: Fish-Man Island Saga",
      "link": "/2024/11/183423.html",
      "poster": "https://s4.anilist.co/file/anilistcdn/media/anime/cover/medium/bx183423-6Iiu194UDxD0.jpg"
    },
    {
      "title": "[ONA] Koisuru ONE PIECE",
      "link": "/2025/04/188668.html",
      "poster": "https://s4.anilist.co/file/anilistcdn/media/anime/cover/medium/bx188668-rOB7rkgOz89w.jpg"
    },
    {
      "title": "[Special] ONE PIECE HEROINES",
      "link": "/2026/07/197178.html",
      "poster": "https://s4.anilist.co/file/anilistcdn/media/anime/cover/medium/bx197178-Ui8PY9HQbNgu.jpg"
    },
    {
      "title": "[Special] ONE PIECE: Original Episode/Luffy, Law",
      "link": "/2025/01/187380.html",
      "poster": "https://s4.anilist.co/file/anilistcdn/media/anime/cover/medium/bx187380-RZmxpJyB3A6Y.jpg"
    },
    {
      "title": "[TV_SHORT] CHOPPER's",
      "link": "/2026/01/204432.html",
      "poster": "https://s4.anilist.co/file/anilistcdn/media/anime/cover/medium/bx204432-h8U4bVnSU6bM.png"
    }
  ],
  "episodes": [],
  "streamingId": "21",
  "releaseDate": "1999-10-20",
  "malId": "",
  "hostUrl": "https://megaplay.buzz/stream/ani"
}